README.rst
setup.py
ZypUtility/ReadConfig.py
ZypUtility/ZypLog.py
ZypUtility/__init__.py
ZypUtility.egg-info/PKG-INFO
ZypUtility.egg-info/SOURCES.txt
ZypUtility.egg-info/dependency_links.txt
ZypUtility.egg-info/top_level.txt